__init__.py
enums.py
ListTransformer.py
listtransformer-0.2.0.dist-info/METADATA
listtransformer-0.2.0.dist-info/WHEEL
listtransformer-0.2.0.dist-info/RECORD
