Metadata-Version: 2.1
Name: ListTransformer
Version: 0.2.0
Summary: My package to convert str-list and list-str.
Home-page: https://tobfd.tech
Author: Tobias Schmitt
Author-email: tobias.schmitt2009@gmail.com
Requires-Python: >=3.10,<4.0
Classifier: Programming Language :: Python :: 3
Classifier: Programming Language :: Python :: 3.10
Classifier: Programming Language :: Python :: 3.11
Classifier: Programming Language :: Python :: 3.12
Project-URL: Documentation, https://github.com/tobfd/ListTransformer
Project-URL: Repository, https://github.com/tobfd/ListTransformer
